{"cameraMode":{"drawMode":0,"name":"Shaded","section":"Shading Mode"},"sceneLighting":false,"audioPlay":false,"sceneViewState":{"m_AlwaysRefresh":false,"showFog":true,"showSkybox":false,"showFlares":true,"showImageEffects":true,"showParticleSystems":true,"showVisualEffectGraphs":true,"m_FxEnabled":true},"in2DMode":false,"pivot":{"x":0.3595268726348877,"y":1.0264077186584473,"z":1.642098069190979},"rotation":{"x":-0.05057366192340851,"y":0.9494782090187073,"z":-0.21970710158348084,"w":-0.21851135790348054},"size":2.126951217651367,"orthographic":false}