{"cameraMode":{"drawMode":0,"name":"Shaded","section":"Shading Mode"},"sceneLighting":false,"audioPlay":false,"sceneViewState":{"m_AlwaysRefresh":false,"showFog":true,"showSkybox":false,"showFlares":true,"showImageEffects":true,"showParticleSystems":true,"showVisualEffectGraphs":true,"m_FxEnabled":true},"in2DMode":false,"pivot":{"x":33.261322021484378,"y":8.901424407958985,"z":5.077579021453857},"rotation":{"x":-0.004499527625739574,"y":0.016793642193078996,"z":-0.00009656955080572516,"w":-0.9998719692230225},"size":0.9284132719039917,"orthographic":false}